[
  {
    "id": 1,
    "name": "xxoo",
    "phone": "18310612838",
    "password": "8376ac810bb9f231d28fcf1f",
    "passwordPay": "510e33c2291ab2d40877acc8",
    "pic": "https://app.youpin.mi.com/youpin/static/m/res/images/evaluation_icon_user.png"
  },
  {
    "id": 2,
    "name": "ooxx",
    "phone": "13041086186",
    "password": "8376ac810bb9f231d28fcf1f",
    "passwordPay": "510e33c2291ab2d40877acc8",
    "pic": "https://app.youpin.mi.com/youpin/static/m/res/images/evaluation_icon_user.png"
  },
  {
    "id": 3,
    "name": "ssdd-前端开发",
    "phone": "18310612830",
    "password": "8376ac810bb9f231d28fcf1f",
    "passwordPay": "510e33c2291ab2d40877acc8",
    "pic": "https://app.youpin.mi.com/youpin/static/m/res/images/evaluation_icon_user.png"
  }
]